datagarden_models/__init__.py
datagarden_models/cli.py
datagarden_models/models/__init__.py
datagarden_models/models/base/__init__.py
datagarden_models/models/base/legend.py
datagarden_models/models/base/metadata.py
datagarden_models/models/base/models.py
datagarden_models/models/base/standard_models.py
datagarden_models/models/demographics/__init__.py
datagarden_models/models/demographics/base_demographics.py
datagarden_models/models/demographics/education.py
datagarden_models/models/demographics/fertility.py
datagarden_models/models/demographics/life_expectancy.py
datagarden_models/models/demographics/migration.py
datagarden_models/models/demographics/mortality.py
datagarden_models/models/demographics/population.py
datagarden_models/models/economics/__init__.py
datagarden_models/models/economics/base_economics.py
datagarden_models/models/economics/gdp.py
datagarden_models/models/economics/inflation.py
datagarden_models/models/economics/investment.py
datagarden_models/models/economics/labor_market.py
datagarden_models/models/economics/productivity.py
datagarden_models/models/economics/public_spending.py
datagarden_models/models/economics/trade.py
datagarden_models/models/health/__init__.py
datagarden_models/models/health/base_health.py
datagarden_models/models/health/death_statistics.py
datagarden_models/models/health/health_care_facilities.py
datagarden_models/models/health/monitor.py
datagarden_models/models/health/vacination_coverage.py
datagarden_models/models/household/__init__.py
datagarden_models/models/household/composition.py
datagarden_models/models/household/economics.py
datagarden_models/models/household/housing.py
datagarden_models/models/social_environment/__init__.py
datagarden_models/models/social_environment/consumer_trust.py
datagarden_models/models/social_environment/local_facilities.py
datagarden_models/models/weather/__init__.py
datagarden_models/models/weather/period_totals.py
datagarden_models/support/__init__.py
the_datagarden_models-1.7.7.dist-info/METADATA
the_datagarden_models-1.7.7.dist-info/WHEEL
the_datagarden_models-1.7.7.dist-info/entry_points.txt
the_datagarden_models-1.7.7.dist-info/top_level.txt
the_datagarden_models-1.7.7.dist-info/RECORD
