Metadata-Version: 2.4
Name: the-datagarden-models
Version: 1.7.7
Summary: Base data models for the datagarden.
Author-email: Maarten de Ruyter <info@the-datagarden.io>
Project-URL: Read the Docs, https://dg-the-datagarden-models.readthedocs.io/en/latest/
Project-URL: The-DataGarden, https://www.the-datagarden.io/
Project-URL: Data Models, https://www.the-datagarden.io/data-docs
Project-URL: Source, https://github.com/OlivettaDataGarden/dg-the-datagarden-models
Keywords: geojson,demographics,economics
Classifier: Programming Language :: Python :: 3
Classifier: Programming Language :: Python :: 3.10
Classifier: Programming Language :: Python :: 3.11
Classifier: Programming Language :: Python :: 3.12
Classifier: Programming Language :: Python :: 3.13
Classifier: License :: OSI Approved :: MIT License
Classifier: Operating System :: OS Independent
Classifier: Development Status :: 5 - Production/Stable
Classifier: Intended Audience :: Developers
Classifier: Intended Audience :: Financial and Insurance Industry
Classifier: Intended Audience :: Science/Research
Classifier: Intended Audience :: Healthcare Industry
Classifier: Topic :: Scientific/Engineering :: GIS
Classifier: Topic :: Scientific/Engineering :: Artificial Intelligence
Classifier: Topic :: Scientific/Engineering :: Information Analysis
Classifier: Topic :: Scientific/Engineering :: Visualization
Classifier: Topic :: Software Development :: Libraries :: Python Modules
Classifier: Topic :: Utilities
Requires-Python: >=3.10
Requires-Dist: click>=8.1.7
Requires-Dist: pydantic>=2.9.2
